mcp_embedded_docs/__init__.py
mcp_embedded_docs/__main__.py
mcp_embedded_docs/config.py
mcp_embedded_docs/indexing/__init__.py
mcp_embedded_docs/indexing/embedder.py
mcp_embedded_docs/indexing/metadata_store.py
mcp_embedded_docs/indexing/vector_store.py
mcp_embedded_docs/ingestion/__init__.py
mcp_embedded_docs/ingestion/chunker.py
mcp_embedded_docs/ingestion/pdf_parser.py
mcp_embedded_docs/ingestion/table_detector.py
mcp_embedded_docs/ingestion/table_extractor.py
mcp_embedded_docs/retrieval/__init__.py
mcp_embedded_docs/retrieval/formatter.py
mcp_embedded_docs/retrieval/hybrid_search.py
mcp_embedded_docs/server.py
mcp_embedded_docs/tools/__init__.py
mcp_embedded_docs/tools/find_register.py
mcp_embedded_docs/tools/ingest_docs.py
mcp_embedded_docs/tools/list_docs.py
mcp_embedded_docs/tools/remove_docs.py
mcp_embedded_docs/tools/search_docs.py
iflow_mcp_michaelayles_mcp_embedded_docs-0.1.0.dist-info/METADATA
iflow_mcp_michaelayles_mcp_embedded_docs-0.1.0.dist-info/WHEEL
iflow_mcp_michaelayles_mcp_embedded_docs-0.1.0.dist-info/entry_points.txt
iflow_mcp_michaelayles_mcp_embedded_docs-0.1.0.dist-info/licenses/LICENSE
iflow_mcp_michaelayles_mcp_embedded_docs-0.1.0.dist-info/RECORD
