Metadata-Version: 2.4
Name: iflow-mcp_michaelayles-mcp-embedded-docs
Version: 0.1.0
Summary: MCP server for embedded systems documentation
License-File: LICENSE
Author: Your Name
Author-email: you@example.com
Requires-Python: >=3.10,<4.0
Classifier: Programming Language :: Python :: 3
Classifier: Programming Language :: Python :: 3.10
Classifier: Programming Language :: Python :: 3.11
Classifier: Programming Language :: Python :: 3.12
Classifier: Programming Language :: Python :: 3.13
Classifier: Programming Language :: Python :: 3.14
Requires-Dist: click (>=8.1.0,<9.0.0)
Requires-Dist: faiss-cpu (>=1.7.4,<2.0.0)
Requires-Dist: httpx (>=0.27.0,<0.28.0)
Requires-Dist: mcp (>=1.0.0,<2.0.0)
Requires-Dist: numpy (>=1.24.0)
Requires-Dist: openai (>=1.6.0,<2.0.0)
Requires-Dist: pdfplumber (>=0.10.0,<0.11.0)
Requires-Dist: pydantic (>=2.5.0,<3.0.0)
Requires-Dist: pymupdf (>=1.23.0,<2.0.0)
Requires-Dist: pyyaml (>=6.0,<7.0)
Requires-Dist: sentence-transformers (>=2.2.0,<3.0.0)
